spsftp/__init__.py
spsftp/spsftp.py
spsftp-0.0.1.dist-info/LICENSE
spsftp-0.0.1.dist-info/WHEEL
spsftp-0.0.1.dist-info/METADATA
spsftp-0.0.1.dist-info/RECORD
